asyncio_cancel_token-0.2.0.dist-info/METADATA
asyncio_cancel_token-0.2.0.dist-info/RECORD
asyncio_cancel_token-0.2.0.dist-info/WHEEL
asyncio_cancel_token-0.2.0.dist-info/top_level.txt
cancel_token/__init__.py
cancel_token/exceptions.py
cancel_token/py.typed
cancel_token/token.py
