Metadata-Version: 2.1
Name: asyncio-cancel-token
Version: 0.2.0
Summary: asyncio-cancel-token: Task cancellation pattern for asyncio applications
Home-page: https://github.com/ethereum/asyncio-cancel-token
Author: Guilherme Salgado
Author-email: gsalgado@gmail.com
License: MIT
Keywords: ethereum
Platform: UNKNOWN
Classifier: Development Status :: 3 - Alpha
Classifier: Intended Audience :: Developers
Classifier: License :: OSI Approved :: MIT License
Classifier: Natural Language :: English
Classifier: Programming Language :: Python :: 3
Classifier: Programming Language :: Python :: 3.6
Classifier: Programming Language :: Python :: 3.7
Classifier: Programming Language :: Python :: Implementation :: PyPy
Requires-Python: >=3.5, <4
Provides-Extra: dev
Provides-Extra: doc
Provides-Extra: lint
Provides-Extra: test
Provides-Extra: dev
Requires-Dist: bumpversion (<1,>=0.5.3); extra == 'dev'
Requires-Dist: pytest-watch (<5,>=4.1.0); extra == 'dev'
Requires-Dist: wheel; extra == 'dev'
Requires-Dist: twine; extra == 'dev'
Requires-Dist: ipython; extra == 'dev'
Requires-Dist: pytest (<5.2,>=5.1); extra == 'dev'
Requires-Dist: pytest-xdist (<1.23,>=1.22); extra == 'dev'
Requires-Dist: pytest-asyncio (==0.10.0); extra == 'dev'
Requires-Dist: tox (<4,>=3.14); extra == 'dev'
Requires-Dist: flake8 (==3.4.1); extra == 'dev'
Requires-Dist: isort (<5,>=4.2.15); extra == 'dev'
Requires-Dist: mypy (==0.720); extra == 'dev'
Requires-Dist: Sphinx (<2,>=1.6.5); extra == 'dev'
Requires-Dist: sphinx-rtd-theme (>=0.1.9); extra == 'dev'
Provides-Extra: doc
Requires-Dist: Sphinx (<2,>=1.6.5); extra == 'doc'
Requires-Dist: sphinx-rtd-theme (>=0.1.9); extra == 'doc'
Provides-Extra: lint
Requires-Dist: flake8 (==3.4.1); extra == 'lint'
Requires-Dist: isort (<5,>=4.2.15); extra == 'lint'
Requires-Dist: mypy (==0.720); extra == 'lint'
Provides-Extra: test
Requires-Dist: pytest (<5.2,>=5.1); extra == 'test'
Requires-Dist: pytest-xdist (<1.23,>=1.22); extra == 'test'
Requires-Dist: pytest-asyncio (==0.10.0); extra == 'test'
Requires-Dist: tox (<4,>=3.14); extra == 'test'
